{
  "aloneexe.htm": "tools/aloneexe.md",
  "anonfn.htm": "language/anonfn.md",
  "banners.htm": "language/banners.md",
  "begin.htm": "language/begin.md",
  "bignum.htm": "intrinsics/classes/bignum.md",
  "build.htm": "tools/build.md",
  "builtins.htm": "intrinsics/builtins.md",
  "bytearr.htm": "intrinsics/classes/bytearr.md",
  "charmap.htm": "language/charmap.md",
  "charset.htm": "intrinsics/classes/charset.md",
  "cmap.htm": "appendices/cmap.md",
  "collect.htm": "intrinsics/classes/collect.md",
  "date.htm": "intrinsics/classes/date.md",
  "dict.htm": "intrinsics/classes/dict.md",
  "dispfn.htm": "language/dispfn.md",
  "dynfunc.htm": "intrinsics/classes/dynfunc.md",
  "dynobj.htm": "language/dynobj.md",
  "enum.htm": "language/enum.md",
  "errmsg.htm": "language/errmsg.md",
  "errtrans.htm": "appendices/errtrans.md",
  "except.htm": "language/except.md",
  "export.htm": "language/export.md",
  "expr.htm": "language/expr.md",
  "file.htm": "intrinsics/classes/file.md",
  "filename.htm": "intrinsics/classes/filename.md",
  "fmt.htm": "language/fmt.md",
  "framedesc.htm": "intrinsics/classes/framedesc.md",
  "gc.htm": "language/gc.md",
  "gramprod.htm": "intrinsics/classes/gramprod.md",
  "hello.htm": "language/hello.md",
  "httpreq.htm": "intrinsics/classes/httpreq.md",
  "httpsrv.htm": "intrinsics/classes/httpsrv.md",
  "icext.htm": "language/icext.md",
  "icic.htm": "intrinsics/classes/icic.md",
  "inherit.htm": "language/inherit.md",
  "init.htm": "language/init.md",
  "inlineobj.htm": "language/inlineobj.md",
  "intro.htm": "language/intro.md",
  "iter.htm": "intrinsics/classes/iter.md",
  "langsec.htm": "language/langsec.md",
  "lib.htm": "language/lib.md",
  "libmisc.htm": "language/libmisc.md",
  "list.htm": "intrinsics/classes/list.md",
  "local.htm": "appendices/local.md",
  "lookup.htm": "intrinsics/classes/lookup.md",
  "multmeth.htm": "language/multmeth.md",
  "namedargs.htm": "language/namedargs.md",
  "naming.htm": "language/naming.md",
  "netsec.htm": "intrinsics/functions/netsec.md",
  "nodef.htm": "language/nodef.md",
  "objdef.htm": "language/objdef.md",
  "objic.htm": "intrinsics/classes/objic.md",
  "opoverload.htm": "language/opoverload.md",
  "optparams.htm": "language/optparams.md",
  "pack.htm": "intrinsics/functions/pack.md",
  "preproc.htm": "language/preproc.md",
  "proccode.htm": "language/proccode.md",
  "progstru.htm": "language/progstru.md",
  "reflect.htm": "language/reflect.md",
  "regex.htm": "intrinsics/functions/regex.md",
  "rexpat.htm": "intrinsics/classes/rexpat.md",
  "scripts.htm": "intrinsics/functions/scripts.md",
  "startup.htm": "language/startup.md",
  "strbuf.htm": "intrinsics/classes/strbuf.md",
  "strcomp.htm": "intrinsics/classes/strcomp.md",
  "string.htm": "intrinsics/classes/string.md",
  "strlit.htm": "language/strlit.md",
  "syntax.htm": "language/syntax.md",
  "t3vm.htm": "intrinsics/functions/t3vm.md",
  "tadsgen.htm": "intrinsics/functions/tadsgen.md",
  "tadsio.htm": "intrinsics/functions/tadsio.md",
  "tadsnet.htm": "intrinsics/functions/tadsnet.md",
  "tadsobj.htm": "intrinsics/classes/tadsobj.md",
  "tempfile.htm": "intrinsics/classes/tempfile.md",
  "terp.htm": "tools/terp.md",
  "timezone.htm": "intrinsics/classes/timezone.md",
  "tok.htm": "language/tok.md",
  "tools.htm": "tools/overview.md",
  "types.htm": "language/types.md",
  "ui.htm": "language/ui.md",
  "undef.htm": "language/undef.md",
  "univpath.htm": "tools/univpath.md",
  "vector.htm": "intrinsics/classes/vector.md",
  "web.htm": "language/web.md",
  "webdeploy.htm": "language/webdeploy.md",
  "webhost.htm": "language/webhost.md",
  "webui.htm": "language/webui.md",
  "wlookup.htm": "intrinsics/classes/wlookup.md"
}